<Room>
  <Saves />
  <index>0A</index>
  <area>00</area>
  <x>38</x>
  <y>04</y>
  <width>01</width>
  <height>04</height>
  <upscroll>70</upscroll>
  <dnscroll>A0</dnscroll>
  <specialGFX>00</specialGFX>
  <Doors>
    <Door>
      <toroom area="00" index="09" />
      <bitflag>00</bitflag>
      <direction>05</direction>
      <tilex>E</tilex>
      <tiley>6</tiley>
      <screenx>06</screenx>
      <screeny>04</screeny>
      <distance>8000</distance>
      <doorcode>0000</doorcode>
    </Door>
    <Door>
      <toroom area="00" index="0B" />
      <bitflag>00</bitflag>
      <direction>06</direction>
      <tilex>6</tilex>
      <tiley>2</tiley>
      <screenx>03</screenx>
      <screeny>00</screeny>
      <distance>8000</distance>
      <doorcode>0000</doorcode>
    </Door>
  </Doors>
  <States>
    <State condition="default">
      <LevelData Width="1" Height="4">
        <Layer1>
          <Screen X="0" Y="0">
        8D11 8D11 8D11 8D11 8D11 8D11 8D11 8D11 8D11 8D11 8D11 8D11 8D11 8D11 8D11 8D11
        8D11 8D11 8D11 8D11 8D11 8D11 8D11 8D11 8D11 8D11 8D11 8D11 8D11 8D11 8D11 8D11
        8D11 8D11 8D11 8D11 8D11 8D11 8D11 8D11 8D11 8D11 8D11 8D11 8D11 8D11 8D11 8D11
        8D11 8D11 8911 8911 8911 8911 8911 8911 8D14 8D0F 890F 8914 8D11 8D11 8D11 8D11
        8D11 8D11 8D14 890F 8914 8D14 8D0F 1D0F 1D0E 00FF 00FF 190E 190F 8914 8D11 8D11
        8918 890F 1D0E 00FF 190E 1D0E 00FF 00FF 00FF 00FF 00FF 00FF 00FF 190E 8914 8D11
        9440 C40C 00FF 00FF 00FF 00FF 00FF 00FF 00FF 00FF 00FF 00FF 00FF 00FF 8110 8D11
        9460 D42C 00FF 00FF 00FF 00FF 00FF 00FF 00FF 00FF 00FF 00FF 00FF 00FF 8110 8D11
        9C60 DC2C 00FF 00FF 00FF 012A 052E 110E 110F 150E 012E 0530 00FF 00FF 190E 8914
        9C40 DC0C 052B 012E 110E 110C 150C 8114 8D11 8504 8501 8500 00FF 00FF 00FF 8110
        8118 810F 810C 850C 8114 8D11 8D11 8D11 8D11 1524 1521 1520 00FF 00FF 00FF 8110
        8D11 8D11 8D11 8D11 8D11 8D11 8D11 8D14 890F 1D0E 00FF 00FF 00FF 00FF 00FF 8110
        8D11 8D11 8D11 8D11 8D11 8D11 8911 8510 00FF 00FF 00FF 00FF 00FF 00FF 110E 8114
        8D11 8D11 8D11 8D11 8D14 8914 1D14 1D0E 00FF 00FF 00FF 00FF 00FF 00FF 8110 8D11
        8D11 8D11 8D14 890F 1D0E 190E 1D0E 00FF 00FF 00FF 00FF 00FF 00FF 110E 8114 8D11
        8D11 8D11 8510 00FF 00FF 00FF 00FF 00FF 00FF 00FF 00FF 00FF 00FF 8110 8D11 8D11
      </Screen>
          <Screen X="0" Y="1">
        8D11 8D14 1D0E 00FF 00FF 00FF 00FF 00FF 00FF 00FF 00FF 00FF 110E 8114 8D11 8D11
        8D11 8510 00FF 00FF 00FF 00FF 00FF 00FF 00FF 00FF 052E 052E 8110 8D11 8D11 8D11
        8D14 1D0E 00FF 00FF 00FF 00FF 00FF 012E 012E 110E 110C 850C 8114 8D11 8D11 8D11
        8510 00FF 00FF 00FF 0130 012E 110E 110C 850C 8114 8D11 8D11 8D11 8D11 8D11 8D11
        8510 00FF 00FF 00FF 8100 8101 8104 8D11 8D11 8D11 8D11 8D11 8D11 8D11 8D11 8D11
        8510 00FF 00FF 00FF 1120 1121 1124 8D11 8D11 8D11 8D11 8D11 8D11 8D11 8D11 8D11
        8514 150E 00FF 00FF 00FF 00FF 190E 190F 8914 8D11 8D11 8D11 8D11 8D11 8D11 8D11
        8D11 8510 00FF 00FF 00FF 00FF 00FF 00FF 190E 190F 8914 8D11 8D11 8D11 8D11 8D11
        8D11 8514 150E 00FF 00FF 00FF 00FF 00FF 00FF 00FF 190E 190F 8914 8D11 8D11 8D11
        8D11 8D11 8510 00FF 00FF 00FF 00FF 00FF 00FF 00FF 00FF 00FF 190E 8914 8D11 8D11
        8D11 8D11 8514 150E 00FF 00FF 00FF 00FF 00FF 00FF 00FF 00FF 00FF 8110 8D11 8D11
        8D11 8D11 8D11 8514 110F 150E 012E 0530 00FF 00FF 00FF 00FF 00FF 190E 8914 8D11
        8D11 8D11 8D11 8D11 8D11 8504 8501 8500 00FF 00FF 00FF 00FF 00FF 00FF 8110 8D11
        8D11 8D11 8D14 890F 8914 1524 1521 1520 00FF 00FF 00FF 00FF 00FF 00FF 190E 8914
        8D11 8D14 1D0E 00FF 190E 1D0E 00FF 00FF 00FF 00FF 00FF 00FF 00FF 00FF 00FF 8110
        8D11 8510 00FF 00FF 00FF 00FF 00FF 00FF 00FF 00FF 00FF 00FF 00FF 00FF 00FF 8110
      </Screen>
          <Screen X="0" Y="2">
        8D11 8510 00FF 00FF 00FF 00FF 00FF 00FF 00FF 012E 012E 012E 00FF 00FF 00FF 8110
        8D14 1D0E 00FF 00FF 00FF 00FF 0130 012E 110E 110C 110B 150C 150E 00FF 110E 8114
        8510 00FF 00FF 00FF 00FF 00FF 8100 8101 8104 8D11 8D11 8D11 8514 810F 8114 8D11
        8510 00FF 00FF 00FF 00FF 00FF 1120 1121 1124 8D11 8D11 8D11 8D11 8D11 8D11 8D11
        8510 00FF 00FF 00FF 00FF 00FF 00FF 00FF 190E 190F 8914 8D11 8D11 8D11 8D11 8D11
        8514 150E 00FF 00FF 00FF 00FF 00FF 00FF 00FF 00FF 190E 190F 8914 8D11 8D11 8D11
        8D11 8510 00FF 00FF 00FF 00FF 00FF 00FF 00FF 00FF 00FF 00FF 190E 8914 8D11 8D11
        8D11 8510 00FF 00FF 00FF 00FF 00FF 00FF 00FF 00FF 00FF 00FF 00FF 8110 8D11 8D11
        8D11 8514 150E 012E 012E 110E 110F 150E 052E 0530 00FF 00FF 00FF 190E 8914 8D11
        8D11 8D11 8514 810C 850C 8114 8D11 8504 8501 8500 00FF 00FF 00FF 00FF 8110 8D11
        8D11 8D11 8D11 8D11 8D11 8D11 8D11 1524 1521 1520 00FF 00FF 00FF 00FF 8110 8D11
        8D11 8D11 8D11 8D11 8D14 8914 8D14 1D0E 00FF 00FF 00FF 00FF 00FF 00FF 8110 8D11
        8D11 8D11 8D14 190F 1D0E 190E 1D0E 00FF 00FF 00FF 00FF 00FF 00FF 110E 8114 8D11
        8D11 8D11 8510 00FF 00FF 00FF 00FF 00FF 00FF 00FF 00FF 00FF 00FF 8110 8D11 8D11
        8D11 8D14 1D0E 00FF 00FF 00FF 00FF 00FF 00FF 0130 012E 110E 110F 8114 8D11 8D11
        8911 8510 00FF 00FF 00FF 00FF 00FF 00FF 00FF 8100 8101 8104 8D11 8D11 8D11 8D11
      </Screen>
          <Screen X="0" Y="3">
        8911 8510 00FF 00FF 00FF 00FF 00FF 00FF 00FF 1120 1121 1124 8D11 8D11 8D11 8D11
        8D11 8510 00FF 00FF 00FF 00FF 00FF 00FF 00FF 00FF 00FF 190E 8914 8D11 8D11 8D11
        8D11 8514 150E 00FF 00FF 00FF 00FF 00FF 00FF 00FF 00FF 00FF 8110 8D11 8D11 8D11
        8D11 8D11 8510 00FF 00FF 00FF 00FF 00FF 00FF 00FF 00FF 00FF 190E 8914 8D11 8D11
        8911 8D11 8514 150E 012E 012E 00FF 00FF 00FF 00FF 00FF 00FF 00FF 8110 8D11 8D11
        8911 8911 8D11 8514 810C 850C 110F 150E 052E 0530 00FF 00FF 00FF 190E 8914 8D11
        8911 8911 8D11 8D11 8D11 8D11 8D11 8504 8501 8500 00FF 00FF 00FF 00FF 8110 8D11
        8911 8911 8D11 8D11 8D14 890F 8914 1524 1521 1520 00FF 00FF 00FF 00FF 8110 8D11
        8911 8911 8911 8D14 1D0E 00FF 190E 1D0E 00FF 00FF 00FF 00FF 00FF 00FF 8110 8D11
        8911 8911 8D11 8510 00FF 00FF 00FF 00FF 00FF 00FF 00FF 00FF 00FF 110E 8114 8D11
        8911 8911 8D11 8510 00FF 00FF 00FF 00FF 00FF 00FF 00FF 00FF 00FF 8110 8D11 8D11
        8911 8911 8D11 8510 00FF 00FF 00FF 00FF 00FF 00FF 00FF 110E 110F 8114 8D11 8D11
        8911 8911 8D11 8514 150E 00FF 00FF 00FF 00FF 00FF 00FF 8110 8D11 8D11 8D11 8D11
        8911 8D11 8D11 8D11 8514 850D C41D 541C 501C 501D 810D 8114 8D11 8D11 8D11 8D11
        8911 8911 8D11 8D11 8911 8519 0443 0442 0042 0043 8119 8D11 8D11 8D11 8D11 8D11
        8D11 8D11 8D11 8D11 8911 8519 9463 9462 9062 9063 8119 8D11 8D11 8D11 8D11 8D11
      </Screen>
        </Layer1>
        <BTS>
          <Screen X="0" Y="0">
        00 00 00 00 00 00 00 00 00 00 00 00 00 00 00 00
        00 00 00 00 00 00 00 00 00 00 00 00 00 00 00 00
        00 00 00 00 00 00 00 00 00 00 00 00 00 00 00 00
        00 00 00 00 00 00 00 00 00 00 00 00 00 00 00 00
        00 00 00 00 00 00 00 D3 D2 00 00 92 D3 00 00 00
        00 00 D2 00 92 D2 00 00 00 00 00 00 00 92 00 00
        00 41 00 00 00 00 00 00 00 00 00 00 00 00 00 00
        00 FF 00 00 00 00 00 00 00 00 00 00 00 00 00 00
        00 FE 00 00 00 00 00 12 53 52 00 00 00 00 92 00
        00 FD 00 00 12 53 53 00 00 00 00 00 00 00 00 00
        00 00 00 00 00 00 00 00 00 D3 D5 D4 00 00 00 00
        00 00 00 00 00 00 00 00 00 D2 00 00 00 00 00 00
        00 00 00 00 00 00 00 00 00 00 00 00 00 00 12 00
        00 00 00 00 00 00 D3 D2 00 00 00 00 00 00 00 00
        00 00 00 00 D2 92 D2 00 00 00 00 00 00 12 00 00
        00 00 00 00 00 00 00 00 00 00 00 00 00 00 00 00
      </Screen>
          <Screen X="0" Y="1">
        00 00 D2 00 00 00 00 00 00 00 00 00 12 00 00 00
        00 00 00 00 00 00 00 00 00 00 00 00 00 00 00 00
        00 D2 00 00 00 00 00 00 00 12 53 00 00 00 00 00
        00 00 00 00 00 00 12 53 00 00 00 00 00 00 00 00
        00 00 00 00 00 00 00 00 00 00 00 00 00 00 00 00
        00 00 00 00 94 95 D3 00 00 00 00 00 00 00 00 00
        00 52 00 00 00 00 92 D3 00 00 00 00 00 00 00 00
        00 00 00 00 00 00 00 00 92 D3 00 00 00 00 00 00
        00 00 52 00 00 00 00 00 00 00 92 D3 00 00 00 00
        00 00 00 00 00 00 00 00 00 00 00 00 92 00 00 00
        00 00 00 52 00 00 00 00 00 00 00 00 00 00 00 00
        00 00 00 00 13 52 00 00 00 00 00 00 00 92 00 00
        00 00 00 00 00 00 00 00 00 00 00 00 00 00 00 00
        00 00 00 00 00 D3 D5 D4 00 00 00 00 00 00 92 00
        00 00 D2 00 92 D2 00 00 00 00 00 00 00 00 00 00
        00 00 00 00 00 00 00 00 00 00 00 00 00 00 00 00
      </Screen>
          <Screen X="0" Y="2">
        00 00 00 00 00 00 00 00 00 00 00 00 00 00 00 00
        00 D2 00 00 00 00 00 00 12 53 53 13 52 00 12 00
        00 00 00 00 00 00 00 00 00 00 00 00 00 00 00 00
        00 00 00 00 00 00 94 95 D3 00 00 00 00 00 00 00
        00 00 00 00 00 00 00 00 92 D3 00 00 00 00 00 00
        00 52 00 00 00 00 00 00 00 00 92 D3 00 00 00 00
        00 00 00 00 00 00 00 00 00 00 00 00 92 00 00 00
        00 00 00 00 00 00 00 00 00 00 00 00 00 00 00 00
        00 00 52 00 00 12 13 52 00 00 00 00 00 92 00 00
        00 00 00 00 00 00 00 00 00 00 00 00 00 00 00 00
        00 00 00 00 00 00 00 93 D5 D4 00 00 00 00 00 00
        00 00 00 00 00 00 00 D2 00 00 00 00 00 00 00 00
        00 00 00 93 D2 92 D2 00 00 00 00 00 00 12 00 00
        00 00 00 00 00 00 00 00 00 00 00 00 00 00 00 00
        00 00 D2 00 00 00 00 00 00 00 00 12 13 00 00 00
        00 00 00 00 00 00 00 00 00 00 00 00 00 00 00 00
      </Screen>
          <Screen X="0" Y="3">
        00 00 00 00 00 00 00 00 00 94 95 93 00 00 00 00
        00 00 00 00 00 00 00 00 00 00 00 92 00 00 00 00
        00 00 52 00 00 00 00 00 00 00 00 00 00 00 00 00
        00 00 00 00 00 00 00 00 00 00 00 00 92 00 00 00
        00 00 00 52 00 00 00 00 00 00 00 00 00 00 00 00
        00 00 00 00 00 00 13 52 00 00 00 00 00 92 00 00
        00 00 00 00 00 00 00 00 00 00 00 00 00 00 00 00
        00 00 00 00 00 00 00 93 D5 D4 00 00 00 00 00 00
        00 00 00 00 D2 00 92 D2 00 00 00 00 00 00 00 00
        00 00 00 00 00 00 00 00 00 00 00 00 00 12 00 00
        00 00 00 00 00 00 00 00 00 00 00 00 00 00 00 00
        00 00 00 00 00 00 00 00 00 00 00 12 53 00 00 00
        00 00 00 00 52 00 00 00 00 00 00 00 00 00 00 00
        00 00 00 00 00 00 42 FF FE FD 00 00 00 00 00 00
        00 00 00 00 00 00 00 00 00 00 00 00 00 00 00 00
        00 00 00 00 00 00 01 01 01 01 00 00 00 00 00 00
      </Screen>
        </BTS>
      </LevelData>
      <GFXset>00</GFXset>
      <music>0000</music>
      <FX1s />
      <Enemies killcount="02">
        <Enemy>
          <ID>E7FF</ID>
          <X>0050</X>
          <Y>0340</Y>
          <tilemap>0000</tilemap>
          <special>A000</special>
          <gfx>0000</gfx>
          <speed>000A</speed>
          <speed2>0000</speed2>
        </Enemy>
        <Enemy>
          <ID>E7FF</ID>
          <X>00A8</X>
          <Y>0200</Y>
          <tilemap>0000</tilemap>
          <special>A000</special>
          <gfx>0000</gfx>
          <speed>000A</speed>
          <speed2>0000</speed2>
        </Enemy>
      </Enemies>
      <EnemyTypes>
        <Enemy>
          <GFX>E7FF</GFX>
          <palette>0001</palette>
        </Enemy>
      </EnemyTypes>
      <layer2_type>BGData</layer2_type>
      <layer2_xscroll>C0</layer2_xscroll>
      <layer2_yscroll>C0</layer2_yscroll>
      <ScrollData const="0001" />
      <roomvar>0000</roomvar>
      <FX2>0000</FX2>
      <PLMs />
      <BGData>
        <Data Type="DECOMP">
          <SOURCE>
            0323 0323 520B 520A 5209 5208 51E1 51E0 11EA 11EB 11EC 11ED 11EC 11ED 10EC 10ED 
            10EE 10EF 11EE 11EF 11EA 11EB 11EA 11EB 11E0 11E1 1208 1209 120A 120B 0323 0323 
            0323 0323 521B 521A 5219 5218 51F1 51F0 11FA 11FB 11FC 11FD 11FC 11FD 10FC 10FD 
            10FE 10FF 11FE 11FF 11FA 11FB 11FA 11FB 11F0 11F1 1218 1219 121A 121B 0323 0323 
            0323 0323 522B 522A 5229 5228 51E1 51E0 11EC 11ED 11EA 11EB 11EC 11ED 11EE 11EF 
            11EE 11EF 11EE 11EF 11EC 11ED 11EA 11EB 11E0 11E1 1228 1229 122A 122B 0323 0323 
            0323 0323 523B 523A 5239 5238 51F1 51F0 11FC 11FD 11FA 11FB 11FC 11FD 11FE 11FF 
            11FE 11FF 11FE 11FF 11FC 11FD 11FA 11FB 11F0 11F1 1238 1239 123A 123B 0323 0323 
            0323 0323 520B 520A 5209 5208 51E1 51E0 11EC 11ED 11EC 11ED 11EC 11ED 11EE 11EF 
            11EE 11EF 11EC 11ED 11EA 11EB 11EA 11EB 11E0 11E1 1208 1209 120A 120B 0323 0323 
            0323 0323 521B 521A 5219 5218 51F1 51F0 11FC 11FD 11FC 11FD 11FC 11FD 11FE 11FF 
            11FE 11FF 11FC 11FD 11FA 11FB 11FA 11FB 11F0 11F1 1218 1219 121A 121B 0323 0323 
            0323 0323 522B 522A 5229 5228 51E1 51E0 10C8 10C9 10CA 10CB 11EC 11ED 11EE 11EF 
            11EE 11EF 11EE 11EF 11EC 11ED 11EA 11EB 11E0 11E1 1228 1229 122A 122B 0323 0323 
            0323 0323 523B 523A 5239 5238 51F1 51F0 10D8 10D9 10DA 10DB 11FC 11FD 11FE 11FF 
            11FE 11FF 11FE 11FF 11FC 11FD 11FA 11FB 11F0 11F1 1238 1239 123A 123B 0323 0323 
            0323 0323 520B 520A 5209 5208 51E1 51E0 10E8 10E9 10EA 10EB 11EC 11ED 11EE 11EF 
            11EE 11EF 11EC 11ED 11EA 11EB 11EA 11EB 11E0 11E1 1208 1209 120A 120B 0323 0323 
            0323 0323 521B 521A 5219 5218 51F1 51F0 10F8 10F9 10FA 10FB 11FC 11FD 11FE 11FF 
            11FE 11FF 11FC 11FD 11FA 11FB 11FA 11FB 11F0 11F1 1218 1219 121A 121B 0323 0323 
            0323 0323 522B 522A 5229 5228 51E1 51E0 11EA 11EB 11EC 11ED 11EE 11EF 11EE 11EF 
            11EE 11EF 11EE 11EF 11EC 11ED 11EA 11EB 11E0 11E1 1228 1229 122A 122B 0323 0323 
            0323 0323 523B 523A 5239 5238 51F1 51F0 11FA 11FB 11FC 11FD 11FE 11FF 11FE 11FF 
            11FE 11FF 11FE 11FF 11FC 11FD 11FA 11FB 11F0 11F1 1238 1239 123A 123B 0323 0323 
            0323 0323 520B 520A 5209 5208 51E1 51E0 11EA 11EB 11EA 11EB 11EC 11ED 11EE 11EF 
            11EE 11EF 11EC 11ED 11EA 11EB 11EA 11EB 11E0 11E1 1208 1209 120A 120B 0323 0323 
            0323 0323 521B 521A 5219 5218 51F1 51F0 11FA 11FB 11FA 11FB 11FC 11FD 11FE 11FF 
            11FE 11FF 11FC 11FD 11FA 11FB 11FA 11FB 11F0 11F1 1218 1219 121A 121B 0323 0323 
            0323 0323 522B 522A 5229 5228 51E1 51E0 11EA 11EB 11EC 11ED 11EE 11EF 10CC 10CD 
            10CE 10CF 11EC 11ED 11EC 11ED 11EA 11EB 11E0 11E1 1228 1229 122A 122B 0323 0323 
            0323 0323 523B 523A 5239 5238 51F1 51F0 11FA 11FB 11FC 11FD 11FE 11FF 10DC 10DD 
            10DE 10DF 11FC 11FD 11FC 11FD 11FA 11FB 11F0 11F1 1238 1239 123A 123B 0323 0323 
            0323 0323 520B 520A 5209 5208 51E1 51E0 11EA 11EB 11EA 11EB 11EE 11EF 10EC 10ED 
            10EE 10EF 11EC 11ED 11EA 11EB 11EC 11ED 11E0 11E1 1208 1209 120A 120B 0323 0323 
            0323 0323 521B 521A 5219 5218 51F1 51F0 11FA 11FB 11FA 11FB 11FE 11FF 10FC 10FD 
            10FE 10FF 11FC 11FD 11FA 11FB 11FC 11FD 11F0 11F1 1218 1219 121A 121B 0323 0323 
            0323 0323 522B 522A 5229 5228 51E1 51E0 11EA 11EB 11EC 11ED 11EE 11EF 11EE 11EF 
            11EE 11EF 11EE 11EF 11EC 11ED 11EC 11ED 11E0 11E1 1228 1229 122A 122B 0323 0323 
            0323 0323 523B 523A 5239 5238 51F1 51F0 11FA 11FB 11FC 11FD 11FE 11FF 11FE 11FF 
            11FE 11FF 11FE 11FF 11FC 11FD 11FC 11FD 11F0 11F1 1238 1239 123A 123B 0323 0323 
            0323 0323 520B 520A 5209 5208 51E1 51E0 11EA 11EB 11EA 11EB 11EC 11ED 11EE 11EF 
            11EE 11EF 11EC 11ED 10C8 10C9 10CA 10CB 11E0 11E1 1208 1209 120A 120B 0323 0323 
            0323 0323 521B 521A 5219 5218 51F1 51F0 11FA 11FB 11FA 11FB 11FC 11FD 11FE 11FF 
            11FE 11FF 11FC 11FD 10D8 10D9 10DA 10DB 11F0 11F1 1218 1219 121A 121B 0323 0323 
            0323 0323 522B 522A 5229 5228 51E1 51E0 11EA 11EB 11EA 11EB 11EA 11EB 11EC 11ED 
            11EE 11EF 11EC 11ED 10E8 10E9 10EA 10EB 11E0 11E1 1228 1229 122A 122B 0323 0323 
            0323 0323 523B 523A 5239 5238 51F1 51F0 11FA 11FB 11FA 11FB 11FA 11FB 11FC 11FD 
            11FE 11FF 11FC 11FD 10F8 10F9 10FA 10FB 11F0 11F1 1238 1239 123A 123B 0323 0323 
            0323 0323 520B 520A 5209 5208 51E1 51E0 11EA 11EB 11EA 11EB 11EC 11ED 11EE 11EF 
            11EE 11EF 11EE 11EF 11EC 11ED 11EC 11ED 11E0 11E1 1208 1209 120A 120B 0323 0323 
            0323 0323 521B 521A 5219 5218 51F1 51F0 11FA 11FB 11FA 11FB 11FC 11FD 11FE 11FF 
            11FE 11FF 11FE 11FF 11FC 11FD 11FC 11FD 11F0 11F1 1218 1219 121A 121B 0323 0323 
            0323 0323 522B 522A 5229 5228 51E1 51E0 11EA 11EB 11EC 11ED 11EE 11EF 11EE 11EF 
            11EE 11EF 11EC 11ED 11EA 11EB 11EC 11ED 11E0 11E1 1228 1229 122A 122B 0323 0323 
            0323 0323 523B 523A 5239 5238 51F1 51F0 11FA 11FB 11FC 11FD 11FE 11FF 11FE 11FF 
            11FE 11FF 11FC 11FD 11FA 11FB 11FC 11FD 11F0 11F1 1238 1239 123A 123B 0323 0323 
            0323 0323 520B 520A 5209 5208 51E1 51E0 11EA 11EB 11EA 11EB 11EC 11ED 11EE 11EF 
            11EE 11EF 11EE 11EF 11EC 11ED 11EA 11EB 11E0 11E1 1208 1209 120A 120B 0323 0323 
            0323 0323 521B 521A 5219 5218 51F1 51F0 11FA 11FB 11FA 11FB 11FC 11FD 11FE 11FF 
            11FE 11FF 11FE 11FF 11FC 11FD 11FA 11FB 11F0 11F1 1218 1219 121A 121B 0323 0323 
            0323 0323 522B 522A 5229 5228 51E1 51E0 11EA 11EB 11EC 11ED 11EE 11EF 10CC 10CD 
            10CE 10CF 11EC 11ED 11EA 11EB 11EA 11EB 11E0 11E1 1228 1229 122A 122B 0323 0323 
            0323 0323 523B 523A 5239 5238 51F1 51F0 11FA 11FB 11FC 11FD 11FE 11FF 10DC 10DD 
            10DE 10DF 11FC 11FD 11FA 11FB 11FA 11FB 11F0 11F1 1238 1239 123A 123B 0323 0323 
          </SOURCE>
          <DEST>4000</DEST>
          <Section>Tiles2</Section>
        </Data>
      </BGData>
      <layer1_2>91D3</layer1_2>
    </State>
  </States>
</Room>