<Room>
  <Saves />
  <index>24</index>
  <area>04</area>
  <x>1A</x>
  <y>0D</y>
  <width>02</width>
  <height>04</height>
  <upscroll>70</upscroll>
  <dnscroll>A0</dnscroll>
  <specialGFX>00</specialGFX>
  <Doors>
    <Door>
      <toroom area="04" index="1C" />
      <bitflag>00</bitflag>
      <direction>05</direction>
      <tilex>E</tilex>
      <tiley>6</tiley>
      <screenx>02</screenx>
      <screeny>00</screeny>
      <distance>8000</distance>
      <doorcode>0000</doorcode>
    </Door>
    <Door>
      <toroom area="04" index="25" />
      <bitflag>00</bitflag>
      <direction>04</direction>
      <tilex>1</tilex>
      <tiley>6</tiley>
      <screenx>00</screenx>
      <screeny>02</screeny>
      <distance>8000</distance>
      <doorcode>0000</doorcode>
    </Door>
    <Door>
      <toroom area="04" index="30" />
      <bitflag>00</bitflag>
      <direction>04</direction>
      <tilex>1</tilex>
      <tiley>6</tiley>
      <screenx>00</screenx>
      <screeny>00</screeny>
      <distance>8000</distance>
      <doorcode>0000</doorcode>
    </Door>
    <Door>
      <toroom area="04" index="24" />
      <bitflag>00</bitflag>
      <direction>05</direction>
      <tilex>E</tilex>
      <tiley>6</tiley>
      <screenx>00</screenx>
      <screeny>03</screeny>
      <distance>8000</distance>
      <doorcode>
        <ScrollData>
          <Change screen="04" scroll="00" />
          <Change screen="07" scroll="00" />
        </ScrollData>
      </doorcode>
    </Door>
  </Doors>
  <States>
    <State condition="default">
      <LevelData Width="2" Height="4">
        <Layer1>
          <Screen X="0" Y="0">
        8176 8177 8178 8179 8176 8177 8178 8179 8176 8177 8178 8179 8176 8177 8178 8179
        8178 8179 8176 8177 8178 8179 8176 8177 8178 8179 8176 8177 8178 8179 8176 8177
        8179 8173 8178 8177 8D61 896D 896D 8961 8175 8D61 896D 896D 8961 8173 8178 8177
        8176 8177 8D61 896D 8D63 00FF 00FF 1960 196D 1D60 00FF 00FF 1960 196D 8961 8177
        8179 8179 8562 00FF 00FF 00FF 00FF 00FF 00FF 00FF 00FF 00FF 00FF 00FF 1960 196D
        8178 8176 8562 00FF 00FF 00FF 00FF 00FF 00FF 00FF 00FF 00FF 00FF 00FF 00FF 00FF
        8176 8D61 1D60 00FF 00FF 00FF 00FF 00FF 00FF 00FF 00FF 00FF 00FF 00FF 00FF 00FF
        8173 8562 00FF 00FF 00FF 00FF 00FF 00FF 00FF 00FF 00FF 00FF 00FF 00FF 00FF 00FF
        8177 8562 00FF 00FF 00FF 00FF 00FF 00FF 00FF 00FF 00FF 00FF 00FF 00FF 00FF 00FF
        8176 8562 00FF 00FF 00FF 00FF 00FF 00FF 00FF 00FF 00FF 00FF 00FF 00FF 00FF 00FF
        8179 8562 00FF 00FF 00FF 00FF 00FF 00FF 00FF 00FF 00FF 00FF 00FF 00FF 00FF 00FF
        8178 8562 00FF 00FF 00FF 00FF 00FF 00FF 00FF 00FF 00FF 00FF 00FF 00FF 8163 816D
        8177 8561 8563 00FF 00FF 00FF 00FF 00FF 00FF 00FF 00FF 00FF 00FF 00FF 8162 8178
        8179 8179 8561 816D 8563 00FF 00FF 00FF 00FF 00FF 00FF 00FF 00FF 8163 8161 8177
        8173 8173 8175 8178 8562 00FF 00FF 00FF 00FF 00FF 00FF 8163 816D 8161 8179 8176
        8178 8D75 8178 8176 8562 00FF 00FF 00FF 00FF 00FF 00FF 8162 8175 8178 8175 8177
      </Screen>
          <Screen X="1" Y="0">
        8176 8177 8178 8179 8176 8177 8178 8179 8176 8177 8178 8179 8176 8177 8178 8179
        8178 8179 8175 8177 8178 8179 8176 8177 8178 8179 8176 8177 8178 8179 8176 8177
        8178 8178 8176 8177 8173 8178 8177 8178 8173 8177 8178 8179 8178 8176 8177 8173
        8178 8178 8178 8179 8177 8175 8179 8176 8176 8177 8177 8177 8178 8178 8179 8178
        8961 8173 8177 8178 8D61 896D 896D 8961 8177 8D61 896D 8961 8176 8175 8176 8177
        8963 8961 8178 8D61 1D60 00FF 00FF 1960 1D6D 1D60 00FF 1960 8961 8173 8178 8179
        00FF 1960 1D6D 1D60 00FF 00FF 00FF 00FF 00FF 00FF 00FF 00FF 8963 8961 8179 8177
        00FF 00FF 00FF 00FF 00FF 00FF 00FF 00FF 00FF 00FF 00FF 00FF 00FF 8162 8177 8173
        00FF 00FF 00FF 00FF 00FF 00FF 00FF 00FF 00FF 00FF 00FF 00FF 00FF 8162 8975 8175
        00FF 00FF 00FF 00FF 00FF 00FF 00FF 00FF 00FF 00FF 00FF 00FF 00FF 1960 8961 8176
        00FF 00FF 00FF 00FF 00FF 00FF 00FF 00FF 00FF 00FF 00FF 00FF 00FF 00FF 8162 8177
        8563 00FF 00FF 00FF 00FF 00FF 00FF 00FF 00FF 00FF 00FF 00FF 00FF 00FF 8162 8178
        8561 8563 00FF 00FF 00FF 00FF 00FF 00FF 00FF 00FF 00FF 00FF 00FF 00FF 8162 8179
        8175 8562 00FF 00FF 00FF 00FF 00FF 00FF 00FF 00FF 00FF 00FF 00FF 00FF 8162 8176
        8175 8562 00FF 00FF 00FF 00FF 00FF 00FF 00FF 00FF 00FF 00FF 00FF 00FF 8162 8177
        8175 8561 816D 8563 00FF 00FF 00FF 00FF 00FF 00FF 00FF 00FF 8163 816D 8161 8179
      </Screen>
          <Screen X="0" Y="1">
        8173 816E 8177 8178 8562 00FF 00FF 00FF 00FF 00FF 00FF 8162 8177 8179 8178 8176
        8177 8177 8173 8179 8562 00FF 00FF 00FF 00FF 00FF 00FF 8162 8179 8173 8179 8179
        8173 8179 8178 8176 8562 00FF 00FF 00FF 00FF 00FF 00FF 8162 8178 8179 8177 8177
        8178 8173 8179 8178 8562 00FF 00FF 00FF 00FF 00FF 00FF 8162 8175 8178 8179 8173
        8177 816E 8175 8179 8562 00FF 00FF 00FF 00FF 00FF 00FF 8162 8178 816E 8173 8177
        8176 8178 8177 8173 8562 00FF 00FF 00FF 00FF 00FF 00FF 8162 8173 8177 8179 8178
        8173 8176 816E 8177 8562 00FF 00FF 00FF 00FF 00FF 00FF 8162 8178 8177 8178 8176
        8177 8177 8175 8178 8562 00FF 00FF 00FF 00FF 00FF 00FF 8162 8175 8178 8176 8178
        8173 8178 8177 8179 8562 00FF 00FF 00FF 00FF 00FF 00FF 8162 816E 8173 8178 8173
        8176 8175 8178 8173 8562 00FF 00FF 00FF 00FF 00FF 00FF 8162 8177 8179 8175 8176
        8177 8178 8173 8178 8562 00FF 00FF 00FF 00FF 00FF 00FF 8162 8173 8177 816E 8178
        8178 8179 8178 8177 8562 00FF 00FF 00FF 00FF 00FF 00FF 8162 8179 8178 8176 8176
        8179 8176 8177 8175 8562 00FF 00FF 00FF 00FF 00FF 00FF 8162 8175 8177 8178 8179
        8173 8177 8175 816E 8562 00FF 00FF 00FF 00FF 00FF 00FF 8162 8176 8178 8179 8176
        8176 816E 8177 8176 8562 00FF 00FF 00FF 00FF 00FF 00FF 8162 8177 8179 8173 8178
        8177 8173 8175 8177 8562 00FF 00FF 00FF 00FF 00FF 00FF 8162 816E 8175 8179 8178
      </Screen>
          <Screen X="1" Y="1">
        8178 8D75 8177 8561 8563 00FF 00FF 00FF 00FF 00FF 00FF 8163 8161 8175 8975 8177
        8177 8173 8179 8176 8562 00FF 00FF 00FF 00FF 00FF 00FF 8162 8173 8179 8176 8177
        8176 8179 8177 8175 8562 00FF 00FF 00FF 00FF 00FF 00FF 8162 8178 8176 8178 8173
        8178 8178 8173 8D61 8D63 00FF 00FF 00FF 00FF 00FF 00FF 8963 8961 8178 8175 8179
        8176 8175 8178 8562 805F B07B B07B B07B B07B B07B B07B 805F 8162 8177 8179 8173
        8173 816E 8176 8561 8563 00FF 00FF 00FF 00FF 00FF 00FF 8163 8161 8173 8177 8176
        8178 8173 8179 8173 8562 00FF 00FF 00FF 00FF 00FF 00FF 8162 8178 8179 8178 8177
        8176 8179 8177 8178 8562 00FF 00FF 00FF 00FF 00FF 00FF 8162 8173 8177 8179 8179
        8177 8177 8178 8179 8562 00FF 00FF 00FF 00FF 00FF 00FF 8162 8179 8176 8175 8177
        8177 8175 8175 8D61 8D63 00FF 00FF 00FF 00FF 00FF 00FF 8963 8961 8179 8177 8177
        8179 8178 8176 8562 805F B07B B07B 807B 807B B07B B07B 805F 8162 8179 8179 8173
        8178 8179 8178 8561 8563 00FF 00FF 00FF 00FF 00FF 00FF 8163 8161 8178 8173 8179
        8176 8173 8177 8177 8562 00FF 00FF 00FF 00FF 00FF 00FF 8162 8175 8179 8178 8173
        8177 8178 8179 8179 8562 00FF 00FF 00FF 00FF 00FF 00FF 8162 8179 8175 8179 8176
        8179 8175 8178 8175 8562 00FF 00FF 00FF 00FF 00FF 00FF 8162 8173 8176 8177 8177
        8173 8179 8176 8D61 8D63 00FF 00FF 00FF 00FF 00FF 00FF 8963 8961 8178 8175 8179
      </Screen>
          <Screen X="0" Y="2">
        8173 8177 8179 8175 8562 00FF 00FF 00FF 00FF 00FF 00FF 8162 8173 8178 8173 8177
        8178 8178 8177 8176 8562 00FF 00FF 00FF 00FF 00FF 00FF 8162 8179 8177 8178 8179
        8179 8176 8178 8177 8562 00FF 00FF 00FF 00FF 00FF 00FF 8162 8178 8179 8177 8176
        8177 8179 8173 8178 8562 00FF 00FF 00FF 00FF 00FF 00FF 8162 8173 8175 8178 8179
        8179 8177 8179 8179 8562 00FF 00FF 00FF 00FF 00FF 00FF 8162 8179 8178 8177 8178
        8176 8178 8177 8173 8562 00FF 00FF 00FF 00FF 00FF 00FF 8162 8177 8177 8179 8177
        8179 8177 8179 8176 8562 00FF 00FF 00FF 00FF 00FF 00FF 8162 8176 8179 8177 8179
        8173 8178 8177 8178 8562 00FF 00FF 00FF 00FF 00FF 00FF 8162 8177 8177 8179 8173
        8178 8177 8173 8179 8562 00FF 00FF 00FF 00FF 00FF 00FF 8162 8177 8173 8178 8179
        8177 8179 8177 8176 8562 00FF 00FF 00FF 00FF 00FF 00FF 8162 8176 8179 8177 8178
        8179 8178 8178 8176 8562 00FF 00FF 00FF 00FF 00FF 00FF 8162 8178 8176 8179 8176
        8178 8173 8177 8179 8562 00FF 00FF 00FF 00FF 00FF 00FF 8162 8178 8179 8176 8178
        8177 8178 8179 8178 8562 00FF 00FF 00FF 00FF 00FF 00FF 8162 8177 8975 8179 8177
        8175 8177 8178 8175 8562 00FF 00FF 00FF 00FF 00FF 00FF 8162 8176 8178 8177 8176
        8178 8177 8179 8179 8562 00FF 00FF 00FF 00FF 00FF 00FF 8162 8173 8178 8179 8177
        8178 8179 8178 8D61 8D63 00FF 00FF 00FF 00FF 00FF 00FF 8963 8961 8177 8173 8179
      </Screen>
          <Screen X="1" Y="2">
        8173 8177 8179 8562 805F 807B 807B B07B B07B 807B 807B 805F 8162 8179 8173 8179
        8178 8179 8173 8561 8563 00FF 00FF 00FF 00FF 00FF 00FF 80BD 8162 8176 8179 8177
        8179 8175 8178 8175 8562 00FF 00FF 00FF 00FF 00FF 00FF 88BD 8963 8D6D 8961 8173
        8177 8178 8176 8178 8562 00FF 00FF 00FF 00FF 00FF 00FF 805F 807B 805F 8162 8178
        8173 8177 8178 8179 8562 00FF 00FF 00FF 00FF 00FF 00FF 0275 0276 8375 8162 8176
        8175 8179 8175 8173 8562 00FF 00FF 00FF 00FF 00FF 00FF 00FF 00FF 805F 8963 8D6D
        8179 8177 8179 8176 8562 00FF 00FF 00FF 00FF 00FF 00FF 00FF 00FF 02C2 C00C 9040
        8176 8179 8177 8178 8562 00FF 00FF 00FF 00FF 00FF 00FF 00FF 00FF 00FF D02C 9060
        8179 8178 8173 8175 8562 00FF 00FF 00FF 00FF 00FF 00FF 00FF 00FF 00FF D82C 9860
        8177 8175 8178 8D61 8D63 00FF 00FF 00FF 00FF 00FF 00FF 00FF 00FF 00FF D80C 9840
        8179 8177 8179 8562 805F B07A B07C 807A 807B 807B 807B 807B 807B 805F 8163 816D
        8176 8173 8177 8562 80BD 00FF 00FF 0275 02DF 0274 00FF 02DF 0276 80BD 8162 8176
        8179 8177 8179 8562 80BE 00FF 00FF 00FF 00FF 00FF 00FF 00FF 00FF 80BE 8162 8179
        8179 8178 8177 8562 88BD 00FF 00FF 00FF 00FF 00FF 00FF 00FF 00FF 88BD 8162 8178
        8178 8177 8179 8562 805F 807B 805F 00FF 00FF 00FF 00FF 805F 807B 805F 8162 8175
        8178 8179 8173 8562 80BD 00FF 00FF 00FF 00FF 00FF 00FF 80BD 8163 816D 8161 8179
      </Screen>
          <Screen X="0" Y="3">
        8179 8175 8179 8562 805F 00FF 00FF 00FF 00FF 00FF 00FF 805F 8162 8179 8177 8176
        8177 8178 8173 8562 80BD 00FF 00FF 00FF 00FF 00FF 00FF 80BD 8162 8175 8179 8175
        8D61 896D 896D 8D63 88BD 00FF 00FF 00FF 00FF 00FF 00FF 88BD 8963 896D 896D 8961
        8562 805F 807B 807B 805F 807B 805F E0B7 805F 807B 807B 805F 807B 807B 805F 8162
        8D63 8375 0275 02DF 00FF 00FF 0276 00FF 00FF 0275 02DF 02C0 0275 0276 8375 8963
        807B 805F 00FF 00FF 00FF 00FF 00FF 00FF 00FF 00FF 00FF 02C1 00FF 00FF 805F 807B
        9440 C40C 00FF 00FF 00FF 00FF 00FF 00FF 00FF 00FF 00FF 00FF 00FF 00FF C00C 9040
        9460 D42C 00FF 00FF 00FF 00FF 00FF 00FF 00FF 00FF 00FF 00FF 00FF 00FF D02C 9060
        9C60 DC2C 00FF 00FF 00FF 00FF 00FF 00FF 00FF 00FF 00FF 00FF 00FF 00FF D82C 9860
        9C40 DC0C 00FF 00FF 00FF 00FF 00FF 00FF 00FF 00FF 00FF 00FF 00FF 00FF D80C 9840
        807B 805F 807B 805F 00FF 00FF 00FF 00FF 00FF 00FF 00FF 00FF 805F 807B 805F 807B
        0675 80BD 02C2 80BD 00FF 00FF 00FF 00FF 00FF 00FF 00FF 00FF 80BD 02C0 80BD 0273
        00FF 80BE 00FF 80BE 00FF 00FF 00FF 00FF 00FF 00FF 00FF 00FF 80BE 02C1 80BE 00FF
        3115 8119 3115 8119 3115 3115 3115 3115 3115 3115 3115 3115 8119 3115 8119 3115
        3116 811A 3116 811A 3116 3116 3116 3116 3116 3116 3116 3116 811A 3116 811A 3116
        8116 811A 8116 811A 8116 8116 8116 8116 8116 8116 8116 8116 811A 8116 811A 8116
      </Screen>
          <Screen X="1" Y="3">
        8179 8176 8178 8562 80BE 00FF 00FF 00FF 00FF 00FF 00FF 80BE 8162 8179 8177 8173
        8975 8179 8177 8562 80BE 00FF 00FF 00FF 00FF 00FF 00FF 80BE 8162 8173 8179 8179
        8D61 896D 896D 8D63 88BD 00FF 00FF 00FF 00FF 00FF 00FF 88BD 8963 896D 896D 8961
        8562 805F 807B 807B 805F C07A 507C 805F 805F C07A 507C 805F 807B 807B 805F 8162
        8D63 8375 02C0 0275 0276 00FF 00FF 0275 02DF 00FF 00FF 02C2 0275 0276 8375 8162
        807B 805F 02C1 00FF 00FF 00FF 00FF 00FF 00FF 00FF 00FF 00FF 00FF 00FF 805F 8162
        9440 C40C 00FF 00FF 00FF 00FF 00FF 00FF 00FF 00FF 00FF 00FF 00FF 00FF 80BD 8162
        9460 D42C 00FF 00FF 00FF 00FF 00FF 00FF 00FF 00FF 00FF 00FF 00FF 00FF 80BE 8162
        9C60 DC2C 00FF 00FF 00FF 00FF 00FF 00FF 00FF 00FF 00FF 00FF 00FF 00FF 80BE 8162
        9C40 DC0C 00FF 00FF 00FF 00FF 00FF 00FF 00FF 00FF 00FF 00FF 00FF 00FF 88BD 8162
        807B 805F 807B 805F 00FF 00FF 00FF 00FF 00FF 00FF 00FF 00FF 805F 807B 805F 8162
        02C1 80BD 0276 80BD 00FF 00FF 00FF 00FF 00FF 00FF 00FF 00FF 80BD 02C2 80BD 8162
        00FF 80BE 00FF 80BE 00FF 00FF 00FF 00FF 00FF 00FF 00FF 00FF 80BE 00FF 80BE 8162
        3115 8119 3115 8119 3115 3115 3115 3115 3115 3115 3115 3115 8119 3115 851B 8162
        3116 811A 3116 811A 3116 3116 3116 3116 3116 3116 3116 3116 811A 3116 851C 8162
        8116 811A 8116 811A 8116 8116 8116 8116 8116 8116 8116 8116 811A 8116 851C 8162
      </Screen>
        </Layer1>
        <BTS>
          <Screen X="0" Y="0">
        00 00 00 00 00 00 00 00 00 00 00 00 00 00 00 00
        00 00 00 00 00 00 00 00 00 00 00 00 00 00 00 00
        00 00 00 00 00 00 00 00 00 00 00 00 00 00 00 00
        00 00 00 00 00 00 00 92 93 D2 00 00 92 93 00 00
        00 00 00 00 00 00 00 00 00 00 00 00 00 00 92 93
        00 00 00 00 00 00 00 00 00 00 00 00 00 00 00 00
        00 00 D2 00 00 00 00 00 00 00 00 00 00 00 00 00
        00 00 00 00 00 00 00 00 00 00 00 00 00 00 00 00
        00 00 00 00 00 00 00 00 00 00 00 00 00 00 00 00
        00 00 00 00 00 00 00 00 00 00 00 00 00 00 00 00
        00 00 00 00 00 00 00 00 00 00 00 00 00 00 00 00
        00 00 00 00 00 00 00 00 00 00 00 00 00 00 00 00
        00 00 00 00 00 00 00 00 00 00 00 00 00 00 00 00
        00 00 00 00 00 00 00 00 00 00 00 00 00 00 00 00
        00 00 00 00 00 00 00 00 00 00 00 00 00 00 00 00
        00 00 00 00 00 00 00 00 00 00 00 00 00 00 00 00
      </Screen>
          <Screen X="1" Y="0">
        00 00 00 00 00 00 00 00 00 00 00 00 00 00 00 00
        00 00 00 00 00 00 00 00 00 00 00 00 00 00 00 00
        00 00 00 00 00 00 00 00 00 00 00 00 00 00 00 00
        00 00 00 00 00 00 00 00 00 00 00 00 00 00 00 00
        00 00 00 00 00 00 00 00 00 00 00 00 00 00 00 00
        00 00 00 00 D2 00 00 92 93 D2 00 92 00 00 00 00
        00 92 93 D2 00 00 00 00 00 00 00 00 00 00 00 00
        00 00 00 00 00 00 00 00 00 00 00 00 00 00 00 00
        00 00 00 00 00 00 00 00 00 00 00 00 00 00 00 00
        00 00 00 00 00 00 00 00 00 00 00 00 00 92 00 00
        00 00 00 00 00 00 00 00 00 00 00 00 00 00 00 00
        00 00 00 00 00 00 00 00 00 00 00 00 00 00 00 00
        00 00 00 00 00 00 00 00 00 00 00 00 00 00 00 00
        00 00 00 00 00 00 00 00 00 00 00 00 00 00 00 00
        00 00 00 00 00 00 00 00 00 00 00 00 00 00 00 00
        00 00 00 00 00 00 00 00 00 00 00 00 00 00 00 00
      </Screen>
          <Screen X="0" Y="1">
        00 00 00 00 00 00 00 00 00 00 00 00 00 00 00 00
        00 00 00 00 00 00 00 00 00 00 00 00 00 00 00 00
        00 00 00 00 00 00 00 00 00 00 00 00 00 00 00 00
        00 00 00 00 00 00 00 00 00 00 00 00 00 00 00 00
        00 00 00 00 00 00 00 00 00 00 00 00 00 00 00 00
        00 00 00 00 00 00 00 00 00 00 00 00 00 00 00 00
        00 00 00 00 00 00 00 00 00 00 00 00 00 00 00 00
        00 00 00 00 00 00 00 00 00 00 00 00 00 00 00 00
        00 00 00 00 00 00 00 00 00 00 00 00 00 00 00 00
        00 00 00 00 00 00 00 00 00 00 00 00 00 00 00 00
        00 00 00 00 00 00 00 00 00 00 00 00 00 00 00 00
        00 00 00 00 00 00 00 00 00 00 00 00 00 00 00 00
        00 00 00 00 00 00 00 00 00 00 00 00 00 00 00 00
        00 00 00 00 00 00 00 00 00 00 00 00 00 00 00 00
        00 00 00 00 00 00 00 00 00 00 00 00 00 00 00 00
        00 00 00 00 00 00 00 00 00 00 00 00 00 00 00 00
      </Screen>
          <Screen X="1" Y="1">
        00 00 00 00 00 00 00 00 00 00 00 00 00 00 00 00
        00 00 00 00 00 00 00 00 00 00 00 00 00 00 00 00
        00 00 00 00 00 00 00 00 00 00 00 00 00 00 00 00
        00 00 00 00 00 00 00 00 00 00 00 00 00 00 00 00
        00 00 00 00 00 04 04 04 04 04 04 00 00 00 00 00
        00 00 00 00 00 00 00 00 00 00 00 00 00 00 00 00
        00 00 00 00 00 00 00 00 00 00 00 00 00 00 00 00
        00 00 00 00 00 00 00 00 00 00 00 00 00 00 00 00
        00 00 00 00 00 00 00 00 00 00 00 00 00 00 00 00
        00 00 00 00 00 00 00 00 00 00 00 00 00 00 00 00
        00 00 00 00 00 04 04 00 00 04 04 00 00 00 00 00
        00 00 00 00 00 00 00 00 00 00 00 00 00 00 00 00
        00 00 00 00 00 00 00 00 00 00 00 00 00 00 00 00
        00 00 00 00 00 00 00 00 00 00 00 00 00 00 00 00
        00 00 00 00 00 00 00 00 00 00 00 00 00 00 00 00
        00 00 00 00 00 00 00 00 00 00 00 00 00 00 00 00
      </Screen>
          <Screen X="0" Y="2">
        00 00 00 00 00 00 00 00 00 00 00 00 00 00 00 00
        00 00 00 00 00 00 00 00 00 00 00 00 00 00 00 00
        00 00 00 00 00 00 00 00 00 00 00 00 00 00 00 00
        00 00 00 00 00 00 00 00 00 00 00 00 00 00 00 00
        00 00 00 00 00 00 00 00 00 00 00 00 00 00 00 00
        00 00 00 00 00 00 00 00 00 00 00 00 00 00 00 00
        00 00 00 00 00 00 00 00 00 00 00 00 00 00 00 00
        00 00 00 00 00 00 00 00 00 00 00 00 00 00 00 00
        00 00 00 00 00 00 00 00 00 00 00 00 00 00 00 00
        00 00 00 00 00 00 00 00 00 00 00 00 00 00 00 00
        00 00 00 00 00 00 00 00 00 00 00 00 00 00 00 00
        00 00 00 00 00 00 00 00 00 00 00 00 00 00 00 00
        00 00 00 00 00 00 00 00 00 00 00 00 00 00 00 00
        00 00 00 00 00 00 00 00 00 00 00 00 00 00 00 00
        00 00 00 00 00 00 00 00 00 00 00 00 00 00 00 00
        00 00 00 00 00 00 00 00 00 00 00 00 00 00 00 00
      </Screen>
          <Screen X="1" Y="2">
        00 00 00 00 00 00 00 00 00 00 00 00 00 00 00 00
        00 00 00 00 00 00 00 00 00 00 00 00 00 00 00 00
        00 00 00 00 00 00 00 00 00 00 00 00 00 00 00 00
        00 00 00 00 00 00 00 00 00 00 00 00 00 00 00 00
        00 00 00 00 00 00 00 00 00 00 00 00 00 00 00 00
        00 00 00 00 00 00 00 00 00 00 00 00 00 00 00 00
        00 00 00 00 00 00 00 00 00 00 00 00 00 00 40 02
        00 00 00 00 00 00 00 00 00 00 00 00 00 00 FF 02
        00 00 00 00 00 00 00 00 00 00 00 00 00 00 FE 02
        00 00 00 00 00 00 00 00 00 00 00 00 00 00 FD 02
        00 00 00 00 00 04 04 00 00 00 00 00 00 00 00 00
        00 00 00 00 00 00 00 00 00 00 00 00 00 00 00 00
        00 00 00 00 00 00 00 00 00 00 00 00 00 00 00 00
        00 00 00 00 00 00 00 00 00 00 00 00 00 00 00 00
        00 00 00 00 00 00 00 00 00 00 00 00 00 00 00 00
        00 00 00 00 00 00 00 00 00 00 00 00 00 00 00 00
      </Screen>
          <Screen X="0" Y="3">
        00 00 00 00 00 00 00 00 00 00 00 00 00 00 00 00
        00 00 00 00 00 00 00 00 00 00 00 00 00 00 00 00
        00 00 00 00 00 00 00 00 00 00 00 00 00 00 00 00
        00 00 00 00 00 00 00 02 00 00 00 00 00 00 00 00
        00 00 00 00 00 00 00 00 00 00 00 00 00 00 00 00
        00 00 00 00 00 00 00 00 00 00 00 00 00 00 00 00
        00 41 00 00 00 00 00 00 00 00 00 00 00 00 40 01
        00 FF 00 00 00 00 00 00 00 00 00 00 00 00 FF 01
        00 FE 00 00 00 00 00 00 00 00 00 00 00 00 FE 01
        00 FD 00 00 00 00 00 00 00 00 00 00 00 00 FD 01
        00 00 00 00 00 00 00 00 00 00 00 00 00 00 00 00
        00 00 00 00 00 00 00 00 00 00 00 00 00 00 00 00
        00 00 00 00 00 00 00 00 00 00 00 00 00 00 00 00
        82 00 82 00 82 82 82 82 82 82 82 82 00 82 00 82
        82 00 82 00 82 82 82 82 82 82 82 82 00 82 00 82
        00 00 00 00 00 00 00 00 00 00 00 00 00 00 00 00
      </Screen>
          <Screen X="1" Y="3">
        00 00 00 00 00 00 00 00 00 00 00 00 00 00 00 00
        00 00 00 00 00 00 00 00 00 00 00 00 00 00 00 00
        00 00 00 00 00 00 00 00 00 00 00 00 00 00 00 00
        00 00 00 00 00 01 FF 00 00 01 FF 00 00 00 00 00
        00 00 00 00 00 00 00 00 00 00 00 00 00 00 00 00
        00 00 00 00 00 00 00 00 00 00 00 00 00 00 00 00
        03 41 00 00 00 00 00 00 00 00 00 00 00 00 00 00
        03 FF 00 00 00 00 00 00 00 00 00 00 00 00 00 00
        03 FE 00 00 00 00 00 00 00 00 00 00 00 00 00 00
        03 FD 00 00 00 00 00 00 00 00 00 00 00 00 00 00
        00 00 00 00 00 00 00 00 00 00 00 00 00 00 00 00
        00 00 00 00 00 00 00 00 00 00 00 00 00 00 00 00
        00 00 00 00 00 00 00 00 00 00 00 00 00 00 00 00
        82 00 82 00 82 82 82 82 82 82 82 82 00 82 00 00
        82 00 82 00 82 82 82 82 82 82 82 82 00 82 00 00
        00 00 00 00 00 00 00 00 00 00 00 00 00 00 00 00
      </Screen>
        </BTS>
        <Layer2>
          <Screen X="0" Y="0">
        014D 014D 014D 014D 014D 014D 014D 014D 0D4D 0D4D 0D4D 0D4D 0D4D 0D4D 0D4D 0D4D
        014D 014D 014D 014D 014D 014D 014D 014D 0D4D 0D4D 0D4D 0D4D 0D4D 0D4D 0D4D 0D4D
        014D 014D 014D 014D 014D 014D 014D 014D 0D4D 0D4D 0D4D 0D4D 0D4D 0D4D 0D4D 0D4D
        014D 014D 014D 014D 014D 014D 014D 014D 0D4D 0D4D 0D4D 0D4D 0D4D 0D4D 0D4D 0D4D
        014D 014D 014D 014D 014D 014D 014D 014D 0D4D 0D4D 0D4D 0D4D 0D4D 0D4D 0D4D 0D4D
        014D 014D 014D 014D 014D 014D 014D 014D 0D4D 0D4D 0D4D 0D4D 0D4D 0D4D 0D4D 0D4D
        014D 014D 014D 014D 014D 014D 014D 014D 0D4D 0D4D 0D4D 0D4D 0D4D 0D4D 0D4D 0D4D
        014D 014D 014D 014D 014D 014D 014D 014D 0D4D 0D4D 0D4D 0D4D 0D4D 0D4D 0D4D 0D4D
        014D 014D 014D 014D 014D 014D 014D 014D 0D4D 0D4D 0D4D 0D4D 0D4D 0D4D 0D4D 0D4D
        014D 014D 014D 014D 014D 014D 014D 014D 0D4D 0D4D 0D4D 0D4D 0D4D 0D4D 0D4D 0D4D
        014D 014D 014D 014D 014D 014D 014D 014D 0D4D 0D4D 0D4D 0D4D 0D4D 0D4D 0D4D 0D4D
        014D 014D 014D 014D 014D 014D 014D 014D 0D4D 0D4D 0D4D 0D4D 0D4D 0D4D 0D4D 0D4D
        014D 014D 014D 014D 014D 014D 014D 014D 0D4D 0D4D 0D4D 0D4D 0D4D 0D4D 0D4D 0D4D
        014D 014D 014D 014D 014D 014D 014D 014D 0D4D 0D4D 0D4D 0D4D 0D4D 0D4D 0D4D 0D4D
        014D 014D 014D 014D 014D 014D 014D 014D 0D4D 0D4D 0D4D 0D4D 0D4D 0D4D 0D4D 0D4D
        014D 014D 014D 014D 014D 014D 014D 014D 0D4D 0D4D 0D4D 0D4D 0D4D 0D4D 0D4D 0D4D
      </Screen>
          <Screen X="1" Y="0">
        014D 014D 014D 014D 014D 014D 014D 014D 0D4D 0D4D 0D4D 0D4D 0D4D 0D4D 0D4D 0D4D
        014D 014D 014D 014D 014D 014D 014D 014D 0D4D 0D4D 0D4D 0D4D 0D4D 0D4D 0D4D 0D4D
        014D 014D 014D 014D 014D 014D 014D 014D 0D4D 0D4D 0D4D 0D4D 0D4D 0D4D 0D4D 0D4D
        014D 014D 014D 014D 014D 014D 014D 014D 0D4D 0D4D 0D4D 0D4D 0D4D 0D4D 0D4D 0D4D
        014D 014D 014D 014D 014D 014D 014D 014D 0D4D 0D4D 0D4D 0D4D 0D4D 0D4D 0D4D 0D4D
        014D 014D 014D 014D 014D 014D 014D 014D 0D4D 0D4D 0D4D 0D4D 0D4D 0D4D 0D4D 0D4D
        014D 014D 014D 014D 014D 014D 014D 014D 0D4D 0D4D 0D4D 0D4D 0D4D 0D4D 0D4D 0D4D
        014D 014D 014D 014D 014D 014D 014D 014D 0D4D 0D4D 0D4D 0D4D 0D4D 0D4D 0D4D 0D4D
        014D 014D 014D 014D 014D 014D 014D 014D 0D4D 0D4D 0D4D 0D4D 0D4D 0D4D 0D4D 0D4D
        014D 014D 014D 014D 014D 014D 014D 014D 0D4D 0D4D 0D4D 0D4D 0D4D 0D4D 0D4D 0D4D
        014D 014D 014D 014D 014D 014D 014D 014D 0D4D 0D4D 0D4D 0D4D 0D4D 0D4D 0D4D 0D4D
        014D 014D 014D 014D 014D 014D 014D 014D 0D4D 0D4D 0D4D 0D4D 0D4D 0D4D 0D4D 0D4D
        014D 014D 014D 014D 014D 014D 014D 014D 0D4D 0D4D 0D4D 0D4D 0D4D 0D4D 0D4D 0D4D
        014D 014D 014D 014D 014D 014D 014D 014D 0D4D 0D4D 0D4D 0D4D 0D4D 0D4D 0D4D 0D4D
        014D 014D 014D 014D 014D 014D 014D 014D 0D4D 0D4D 0D4D 0D4D 0D4D 0D4D 0D4D 0D4D
        014D 014D 014D 014D 014D 014D 014D 014D 0D4D 0D4D 0D4D 0D4D 0D4D 0D4D 0D4D 0D4D
      </Screen>
          <Screen X="0" Y="1">
        054D 054D 054D 054D 014D 014D 014D 014D 0D4D 0D4D 0D4D 0D4D 094D 094D 094D 094D
        054D 054D 054D 054D 014D 014D 014D 014D 0D4D 0D4D 0D4D 0D4D 094D 094D 094D 094D
        054D 054D 054D 054D 014D 014D 014D 014D 0D4D 0D4D 0D4D 0D4D 094D 094D 094D 094D
        054D 054D 054D 054D 014D 014D 014D 014D 0D4D 0D4D 0D4D 0D4D 094D 094D 094D 094D
        054D 054D 054D 054D 014D 014D 014D 014D 0D4D 0D4D 0D4D 0D4D 094D 094D 094D 094D
        054D 054D 054D 054D 014D 014D 014D 014D 0D4D 0D4D 0D4D 0D4D 094D 094D 094D 094D
        054D 054D 054D 054D 014D 014D 014D 014D 0D4D 0D4D 0D4D 0D4D 094D 094D 094D 094D
        054D 054D 054D 054D 014D 014D 014D 014D 0D4D 0D4D 0D4D 0D4D 094D 094D 094D 094D
        054D 054D 054D 054D 014D 014D 014D 014D 0D4D 0D4D 0D4D 0D4D 094D 094D 094D 094D
        054D 054D 054D 054D 014D 014D 014D 014D 0D4D 0D4D 0D4D 0D4D 094D 094D 094D 094D
        054D 054D 054D 054D 014D 014D 014D 014D 0D4D 0D4D 0D4D 0D4D 094D 094D 094D 094D
        054D 054D 054D 054D 014D 014D 014D 014D 0D4D 0D4D 0D4D 0D4D 094D 094D 094D 094D
        054D 054D 054D 054D 014D 014D 014D 014D 0D4D 0D4D 0D4D 0D4D 094D 094D 094D 094D
        054D 054D 054D 054D 014D 014D 014D 014D 0D4D 0D4D 0D4D 0D4D 094D 094D 094D 094D
        054D 054D 054D 054D 014D 014D 014D 014D 0D4D 0D4D 0D4D 0D4D 094D 094D 094D 094D
        054D 054D 054D 054D 014D 014D 014D 014D 0D4D 0D4D 0D4D 0D4D 094D 094D 094D 094D
      </Screen>
          <Screen X="1" Y="1">
        054D 054D 054D 054D 014D 014D 014D 014D 0D4D 0D4D 0D4D 0D4D 0D4D 0D4D 0D4D 0D4D
        054D 054D 054D 054D 014D 014D 014D 014D 0D4D 0D4D 0D4D 0D4D 0D4D 0D4D 0D4D 0D4D
        054D 054D 054D 054D 014D 014D 014D 014D 0D4D 0D4D 0D4D 0D4D 0D4D 0D4D 0D4D 0D4D
        054D 054D 054D 054D 014D 014D 014D 014D 0D4D 0D4D 0D4D 0D4D 0D4D 0D4D 0D4D 0D4D
        054D 054D 054D 054D 014D 014D 014D 014D 0D4D 0D4D 0D4D 0D4D 0D4D 0D4D 0D4D 0D4D
        054D 054D 054D 054D 014D 014D 014D 014D 0D4D 0D4D 0D4D 0D4D 0D4D 0D4D 0D4D 0D4D
        054D 054D 054D 054D 014D 014D 014D 014D 0D4D 0D4D 0D4D 0D4D 0D4D 0D4D 0D4D 0D4D
        054D 054D 054D 054D 014D 014D 014D 014D 0D4D 0D4D 0D4D 0D4D 0D4D 0D4D 0D4D 0D4D
        054D 054D 054D 054D 014D 014D 014D 014D 0D4D 0D4D 0D4D 0D4D 0D4D 0D4D 0D4D 0D4D
        054D 054D 054D 054D 014D 014D 014D 014D 0D4D 0D4D 0D4D 0D4D 0D4D 0D4D 0D4D 0D4D
        054D 054D 054D 054D 014D 014D 014D 014D 0D4D 0D4D 0D4D 0D4D 0D4D 0D4D 0D4D 0D4D
        054D 054D 054D 054D 014D 014D 014D 014D 0D4D 0D4D 0D4D 0D4D 0D4D 0D4D 0D4D 0D4D
        054D 054D 054D 054D 014D 014D 014D 014D 0D4D 0D4D 0D4D 0D4D 0D4D 0D4D 0D4D 0D4D
        054D 054D 054D 054D 014D 014D 014D 014D 0D4D 0D4D 0D4D 0D4D 0D4D 0D4D 0D4D 0D4D
        054D 054D 054D 054D 014D 014D 014D 014D 0D4D 0D4D 0D4D 0D4D 0D4D 0D4D 0D4D 0D4D
        054D 054D 054D 054D 014D 014D 014D 014D 0D4D 0D4D 0D4D 0D4D 0D4D 0D4D 0D4D 0D4D
      </Screen>
          <Screen X="0" Y="2">
        054D 054D 054D 054D 014D 014D 014D 014D 0D4D 0D4D 0D4D 0D4D 094D 094D 094D 014D
        054D 054D 054D 054D 014D 014D 014D 014D 0D4D 0D4D 0D4D 0D4D 094D 094D 094D 014D
        054D 054D 054D 054D 014D 014D 014D 014D 0D4D 0D4D 0D4D 0D4D 094D 094D 094D 014D
        054D 054D 054D 054D 014D 014D 014D 014D 0D4D 0D4D 0D4D 0D4D 094D 094D 094D 014D
        054D 054D 054D 054D 014D 014D 014D 014D 0D4D 0D4D 0D4D 0D4D 094D 094D 094D 014D
        054D 054D 054D 054D 014D 014D 014D 014D 0D4D 0D4D 0D4D 0D4D 094D 094D 094D 014D
        054D 054D 054D 054D 014D 014D 014D 014D 0D4D 0D4D 0D4D 0D4D 094D 094D 094D 014D
        054D 054D 054D 054D 014D 014D 014D 014D 0D4D 0D4D 0D4D 0D4D 094D 094D 094D 014D
        054D 054D 054D 054D 014D 014D 014D 014D 0D4D 0D4D 0D4D 0D4D 094D 094D 094D 014D
        054D 054D 054D 054D 014D 014D 014D 014D 0D4D 0D4D 0D4D 0D4D 094D 094D 094D 014D
        054D 054D 054D 054D 014D 014D 014D 014D 0D4D 0D4D 0D4D 0D4D 094D 094D 094D 014D
        054D 054D 054D 054D 014D 014D 014D 014D 0D4D 0D4D 0D4D 0D4D 094D 094D 094D 014D
        054D 054D 054D 054D 014D 014D 014D 014D 0D4D 0D4D 0D4D 0D4D 094D 094D 094D 014D
        054D 054D 054D 054D 014D 014D 014D 014D 0D4D 0D4D 0D4D 0D4D 094D 094D 094D 014D
        054D 054D 054D 054D 014D 014D 014D 014D 0D4D 0D4D 0D4D 0D4D 094D 094D 094D 014D
        054D 054D 054D 054D 014D 014D 014D 014D 0D4D 0D4D 0D4D 0D4D 094D 094D 094D 014D
      </Screen>
          <Screen X="1" Y="2">
        054D 054D 054D 054D 014D 014D 014D 014D 0D4D 0D4D 0D4D 0D4D 0D4D 0D4D 0D4D 0D4D
        054D 054D 054D 054D 014D 014D 014D 014D 0D4D 0D4D 0D4D 0D4D 0D4D 0D4D 0D4D 0D4D
        054D 054D 054D 054D 014D 014D 014D 014D 0D4D 0D4D 0D4D 0D4D 0D4D 0D4D 0D4D 0D4D
        054D 054D 054D 054D 014D 014D 014D 014D 0D4D 0D4D 0D4D 0D4D 0D4D 0D4D 0D4D 0D4D
        054D 054D 054D 054D 014D 014D 014D 014D 0D4D 0D4D 0D4D 0D4D 0D4D 0D4D 0D4D 0D4D
        054D 054D 054D 054D 014D 014D 014D 014D 0D4D 0D4D 0D4D 0D4D 0D4D 0D4D 0D4D 0D4D
        054D 054D 054D 054D 014D 014D 014D 014D 0D4D 0D4D 0D4D 0D4D 0D4D 0D4D 0D4D 0D4D
        054D 054D 054D 054D 014D 014D 014D 014D 0D4D 0D4D 0D4D 0D4D 0D4D 0D4D 0D4D 0D4D
        054D 054D 054D 054D 014D 014D 014D 014D 0D4D 0D4D 0D4D 0D4D 0D4D 0D4D 0D4D 0D4D
        054D 054D 054D 054D 014D 014D 014D 014D 0D4D 0D4D 0D4D 0D4D 0D4D 0D4D 0D4D 0D4D
        054D 054D 054D 054D 014D 014D 014D 014D 0D4D 0D4D 0D4D 0D4D 0D4D 0D4D 0D4D 0D4D
        054D 054D 054D 054D 014D 014D 014D 014D 0D4D 0D4D 0D4D 0D4D 0D4D 0D4D 0D4D 0D4D
        054D 054D 054D 054D 014D 014D 014D 014D 0D4D 0D4D 0D4D 0D4D 0D4D 0D4D 0D4D 0D4D
        054D 054D 054D 054D 014D 014D 014D 014D 0D4D 0D4D 0D4D 0D4D 0D4D 0D4D 0D4D 0D4D
        054D 054D 054D 054D 014D 014D 014D 014D 0D4D 0D4D 0D4D 0D4D 0D4D 0D4D 0D4D 0D4D
        054D 054D 054D 054D 014D 014D 014D 014D 0D4D 0D4D 0D4D 0D4D 0D4D 0D4D 0D4D 0D4D
      </Screen>
          <Screen X="0" Y="3">
        014D 014D 014D 014D 014D 014D 014D 014D 0D4D 0D4D 0D4D 0D4D 0D4D 0D4D 0D4D 0D4D
        014D 014D 014D 014D 014D 014D 014D 014D 0D4D 0D4D 0D4D 0D4D 0D4D 0D4D 0D4D 0D4D
        014D 014D 014D 014D 014D 014D 014D 014D 0D4D 0D4D 0D4D 0D4D 0D4D 0D4D 0D4D 0D4D
        014D 014D 014D 014D 014D 014D 014D 014D 0D4D 0D4D 0D4D 0D4D 0D4D 0D4D 0D4D 0D4D
        014D 014D 014D 014D 014D 014D 014D 014D 0D4D 0D4D 0D4D 0D4D 0D4D 0D4D 0D4D 0D4D
        014D 014D 014D 014D 014D 014D 014D 014D 0D4D 0D4D 0D4D 0D4D 0D4D 0D4D 0D4D 0D4D
        014D 014D 014D 014D 014D 014D 014D 014D 0D4D 0D4D 0D4D 0D4D 0D4D 0D4D 0D4D 0D4D
        014D 014D 014D 014D 014D 014D 014D 014D 0D4D 0D4D 0D4D 0D4D 0D4D 0D4D 0D4D 0D4D
        014D 014D 014D 014D 014D 014D 014D 014D 0D4D 0D4D 0D4D 0D4D 0D4D 0D4D 0D4D 0D4D
        014D 014D 014D 014D 014D 014D 014D 014D 0D4D 0D4D 0D4D 0D4D 0D4D 0D4D 0D4D 0D4D
        014D 014D 014D 014D 014D 014D 014D 014D 0D4D 0D4D 0D4D 0D4D 0D4D 0D4D 0D4D 0D4D
        014D 014D 014D 014D 014D 014D 014D 014D 0D4D 0D4D 0D4D 0D4D 0D4D 0D4D 0D4D 0D4D
        014D 014D 014D 014D 014D 014D 014D 014D 0D4D 0D4D 0D4D 0D4D 0D4D 0D4D 0D4D 0D4D
        014D 014D 014D 014D 014D 014D 014D 014D 0D4D 0D4D 0D4D 0D4D 0D4D 0D4D 0D4D 0D4D
        014D 014D 014D 014D 014D 014D 014D 014D 0D4D 0D4D 0D4D 0D4D 0D4D 0D4D 0D4D 0D4D
        014D 014D 014D 014D 014D 014D 014D 014D 0D4D 0D4D 0D4D 0D4D 0D4D 0D4D 0D4D 0D4D
      </Screen>
          <Screen X="1" Y="3">
        014D 014D 014D 014D 014D 014D 014D 014D 0D4D 0D4D 0D4D 0D4D 0D4D 0D4D 0D4D 0D4D
        014D 014D 014D 014D 014D 014D 014D 014D 0D4D 0D4D 0D4D 0D4D 0D4D 0D4D 0D4D 0D4D
        014D 014D 014D 014D 014D 014D 014D 014D 0D4D 0D4D 0D4D 0D4D 0D4D 0D4D 0D4D 0D4D
        014D 014D 014D 014D 014D 014D 014D 014D 0D4D 0D4D 0D4D 0D4D 0D4D 0D4D 0D4D 0D4D
        014D 014D 014D 014D 014D 014D 014D 014D 0D4D 0D4D 0D4D 0D4D 0D4D 0D4D 0D4D 0D4D
        014D 014D 014D 014D 014D 014D 014D 014D 0D4D 0D4D 0D4D 0D4D 0D4D 0D4D 0D4D 0D4D
        014D 014D 014D 014D 014D 014D 014D 014D 0D4D 0D4D 0D4D 0D4D 0D4D 0D4D 0D4D 0D4D
        014D 014D 014D 014D 014D 014D 014D 014D 0D4D 0D4D 0D4D 0D4D 0D4D 0D4D 0D4D 0D4D
        014D 014D 014D 014D 014D 014D 014D 014D 0D4D 0D4D 0D4D 0D4D 0D4D 0D4D 0D4D 0D4D
        014D 014D 014D 014D 014D 014D 014D 014D 0D4D 0D4D 0D4D 0D4D 0D4D 0D4D 0D4D 0D4D
        014D 014D 014D 014D 014D 014D 014D 014D 0D4D 0D4D 0D4D 0D4D 0D4D 0D4D 0D4D 0D4D
        014D 014D 014D 014D 014D 014D 014D 014D 0D4D 0D4D 0D4D 0D4D 0D4D 0D4D 0D4D 0D4D
        014D 014D 014D 014D 014D 014D 014D 014D 0D4D 0D4D 0D4D 0D4D 0D4D 0D4D 0D4D 0D4D
        014D 014D 014D 014D 014D 014D 014D 014D 0D4D 0D4D 0D4D 0D4D 0D4D 0D4D 0D4D 0D4D
        014D 014D 014D 014D 014D 014D 014D 014D 0D4D 0D4D 0D4D 0D4D 0D4D 0D4D 0D4D 0D4D
        014D 014D 014D 014D 014D 014D 014D 014D 0D4D 0D4D 0D4D 0D4D 0D4D 0D4D 0D4D 0D4D
      </Screen>
        </Layer2>
      </LevelData>
      <GFXset>0C</GFXset>
      <music>0000</music>
      <FX1s>
        <FX1 default="true">
          <surfacestart>02B0</surfacestart>
          <surfacenew>FFFF</surfacenew>
          <surfacespeed>0000</surfacespeed>
          <surfacedelay>00</surfacedelay>
          <type>06</type>
          <transparency1_A>02</transparency1_A>
          <transparency2_B>14</transparency2_B>
          <liquidflags_C>82</liquidflags_C>
          <paletteflags>01</paletteflags>
          <animationflags>00</animationflags>
          <paletteblend>E8</paletteblend>
        </FX1>
      </FX1s>
      <Enemies killcount="07">
        <Enemy>
          <ID>D17F</ID>
          <X>0050</X>
          <Y>0050</Y>
          <tilemap>0000</tilemap>
          <special>2000</special>
          <gfx>0000</gfx>
          <speed>0000</speed>
          <speed2>0000</speed2>
        </Enemy>
        <Enemy>
          <ID>D17F</ID>
          <X>0030</X>
          <Y>0078</Y>
          <tilemap>0000</tilemap>
          <special>2000</special>
          <gfx>0000</gfx>
          <speed>0000</speed>
          <speed2>0000</speed2>
        </Enemy>
        <Enemy>
          <ID>D17F</ID>
          <X>00B8</X>
          <Y>0050</Y>
          <tilemap>0000</tilemap>
          <special>2000</special>
          <gfx>0000</gfx>
          <speed>0000</speed>
          <speed2>0000</speed2>
        </Enemy>
        <Enemy>
          <ID>CFBF</ID>
          <X>0170</X>
          <Y>029C</Y>
          <tilemap>0000</tilemap>
          <special>2000</special>
          <gfx>0000</gfx>
          <speed>0080</speed>
          <speed2>0016</speed2>
        </Enemy>
        <Enemy>
          <ID>CFBF</ID>
          <X>0160</X>
          <Y>01FC</Y>
          <tilemap>0000</tilemap>
          <special>2000</special>
          <gfx>0000</gfx>
          <speed>0080</speed>
          <speed2>0016</speed2>
        </Enemy>
        <Enemy>
          <ID>D17F</ID>
          <X>0170</X>
          <Y>0078</Y>
          <tilemap>0000</tilemap>
          <special>2000</special>
          <gfx>0000</gfx>
          <speed>0000</speed>
          <speed2>0000</speed2>
        </Enemy>
        <Enemy>
          <ID>D17F</ID>
          <X>0198</X>
          <Y>0070</Y>
          <tilemap>0000</tilemap>
          <special>2000</special>
          <gfx>0000</gfx>
          <speed>0000</speed>
          <speed2>0000</speed2>
        </Enemy>
        <Enemy>
          <ID>D17F</ID>
          <X>0090</X>
          <Y>0070</Y>
          <tilemap>0000</tilemap>
          <special>2000</special>
          <gfx>0000</gfx>
          <speed>0000</speed>
          <speed2>0000</speed2>
        </Enemy>
        <Enemy>
          <ID>CFBF</ID>
          <X>01C0</X>
          <Y>02DC</Y>
          <tilemap>0000</tilemap>
          <special>2000</special>
          <gfx>0000</gfx>
          <speed>0020</speed>
          <speed2>0016</speed2>
        </Enemy>
        <Enemy>
          <ID>CFBF</ID>
          <X>0180</X>
          <Y>032C</Y>
          <tilemap>0000</tilemap>
          <special>2000</special>
          <gfx>0000</gfx>
          <speed>0030</speed>
          <speed2>0016</speed2>
        </Enemy>
        <Enemy>
          <ID>CFBF</ID>
          <X>01A0</X>
          <Y>019C</Y>
          <tilemap>0000</tilemap>
          <special>2000</special>
          <gfx>0000</gfx>
          <speed>0040</speed>
          <speed2>0016</speed2>
        </Enemy>
        <Enemy>
          <ID>CFBF</ID>
          <X>0150</X>
          <Y>03F0</Y>
          <tilemap>0000</tilemap>
          <special>2000</special>
          <gfx>0000</gfx>
          <speed>0010</speed>
          <speed2>0008</speed2>
        </Enemy>
        <Enemy>
          <ID>CFBF</ID>
          <X>01B0</X>
          <Y>03F0</Y>
          <tilemap>0000</tilemap>
          <special>2000</special>
          <gfx>0000</gfx>
          <speed>0008</speed>
          <speed2>0008</speed2>
        </Enemy>
      </Enemies>
      <EnemyTypes>
        <Enemy>
          <GFX>D17F</GFX>
          <palette>0001</palette>
        </Enemy>
        <Enemy>
          <GFX>CFBF</GFX>
          <palette>0002</palette>
        </Enemy>
        <Enemy>
          <GFX>D7FF</GFX>
          <palette>0002</palette>
        </Enemy>
      </EnemyTypes>
      <layer2_type>Layer2</layer2_type>
      <layer2_xscroll>00</layer2_xscroll>
      <layer2_yscroll>C0</layer2_yscroll>
      <ScrollData>02 02 02 02 02 01 01 00 </ScrollData>
      <roomvar>0000</roomvar>
      <FX2>0000</FX2>
      <PLMs>
        <PLM>
          <type>B703</type>
          <x>06</x>
          <y>32</y>
          <ScrollData>
            <Change screen="02" scroll="02" />
            <Change screen="03" scroll="00" />
            <Change screen="04" scroll="02" />
            <Change screen="05" scroll="00" />
            <Change screen="06" scroll="01" />
            <Change screen="07" scroll="00" />
          </ScrollData>
        </PLM>
        <PLM>
          <type>B63B</type>
          <x>07</x>
          <y>32</y>
          <arg>8000</arg>
        </PLM>
        <PLM>
          <type>B63B</type>
          <x>08</x>
          <y>32</y>
          <arg>8000</arg>
        </PLM>
        <PLM>
          <type>B63B</type>
          <x>09</x>
          <y>32</y>
          <arg>8000</arg>
        </PLM>
        <PLM>
          <type>B703</type>
          <x>0D</x>
          <y>0C</y>
          <ScrollData>
            <Change screen="02" scroll="02" />
            <Change screen="03" scroll="00" />
            <Change screen="04" scroll="02" />
            <Change screen="05" scroll="00" />
            <Change screen="06" scroll="01" />
            <Change screen="07" scroll="00" />
          </ScrollData>
        </PLM>
        <PLM>
          <type>B647</type>
          <x>0D</x>
          <y>0B</y>
          <arg>8000</arg>
        </PLM>
        <PLM>
          <type>B647</type>
          <x>0D</x>
          <y>0A</y>
          <arg>8000</arg>
        </PLM>
        <PLM>
          <type>B647</type>
          <x>0D</x>
          <y>09</y>
          <arg>8000</arg>
        </PLM>
        <PLM>
          <type>B647</type>
          <x>0D</x>
          <y>08</y>
          <arg>8000</arg>
        </PLM>
        <PLM>
          <type>B647</type>
          <x>0D</x>
          <y>07</y>
          <arg>8000</arg>
        </PLM>
        <PLM>
          <type>B647</type>
          <x>0D</x>
          <y>06</y>
          <arg>8000</arg>
        </PLM>
        <PLM>
          <type>B647</type>
          <x>0D</x>
          <y>05</y>
          <arg>8000</arg>
        </PLM>
        <PLM>
          <type>B647</type>
          <x>0D</x>
          <y>04</y>
          <arg>8000</arg>
        </PLM>
        <PLM>
          <type>B703</type>
          <x>12</x>
          <y>0E</y>
          <ScrollData>
            <Change screen="02" scroll="00" />
            <Change screen="03" scroll="02" />
            <Change screen="04" scroll="00" />
            <Change screen="05" scroll="01" />
            <Change screen="06" scroll="00" />
          </ScrollData>
        </PLM>
        <PLM>
          <type>B647</type>
          <x>12</x>
          <y>0D</y>
          <arg>8000</arg>
        </PLM>
        <PLM>
          <type>B647</type>
          <x>12</x>
          <y>0C</y>
          <arg>8000</arg>
        </PLM>
        <PLM>
          <type>B647</type>
          <x>12</x>
          <y>0B</y>
          <arg>8000</arg>
        </PLM>
        <PLM>
          <type>B647</type>
          <x>12</x>
          <y>0A</y>
          <arg>8000</arg>
        </PLM>
        <PLM>
          <type>B647</type>
          <x>12</x>
          <y>09</y>
          <arg>8000</arg>
        </PLM>
        <PLM>
          <type>B647</type>
          <x>12</x>
          <y>08</y>
          <arg>8000</arg>
        </PLM>
        <PLM>
          <type>B647</type>
          <x>12</x>
          <y>07</y>
          <arg>8000</arg>
        </PLM>
        <PLM>
          <type>B703</type>
          <x>15</x>
          <y>2B</y>
          <ScrollData>
            <Change screen="05" scroll="02" />
            <Change screen="07" scroll="01" />
          </ScrollData>
        </PLM>
        <PLM>
          <type>B63B</type>
          <x>16</x>
          <y>2B</y>
          <arg>8000</arg>
        </PLM>
        <PLM>
          <type>B63B</type>
          <x>17</x>
          <y>2B</y>
          <arg>8000</arg>
        </PLM>
      </PLMs>
      <BGData />
      <layer1_2>C8D2</layer1_2>
    </State>
  </States>
</Room>